[{"stock":"K1","name":"K-ONE TECHNOLOGY BHD"},{"stock":"KAMDAR","name":"KAMDAR GROUP(M)BHD"},{"stock":"KANGER","name":"KANGER INTERNATIONAL BERHAD"},{"stock":"KANGER-WA","name":"KANGER INTERNATIONAL BERHAD"},{"stock":"KAREX","name":"KAREX BERHAD"},{"stock":"KAREX-CN","name":"KAREX-CN: CW KAREX BERHAD (MIBB)"},{"stock":"KAREX-CO","name":"KAREX-CO: CW KAREX BERHAD (MIBB)"},{"stock":"KAREX-CQ","name":"KAREX-CQ: CW KAREX BERHAD (MACQ)"},{"stock":"KAREX-CR","name":"KAREX-CR: CW KAREX BERHAD (RHB)"},{"stock":"KAREX-CS","name":"KAREX-CS: CW KAREX BERHAD (KIBB)"},{"stock":"KAREX-CT","name":"KAREX-CT: CW KAREX BERHAD (MIBB)"},{"stock":"KAREX-CU","name":"KAREX-CU: CW KAREX BERHAD (MIBB)"},{"stock":"KAREX-CV","name":"KAREX-CV: CW KAREX BERHAD (MIBB)"},{"stock":"KARYON","name":"KARYON INDUSTRIES BHD"},{"stock":"KAWAN","name":"KAWAN FOOD BHD"},{"stock":"KBES","name":"KBES BHD"},{"stock":"KBUNAI","name":"KARAMBUNAI CORP BHD"},{"stock":"KBUNAI-WC","name":"KARAMBUNAI CORP BHD -WC 13/23"},{"stock":"KEINHIN","name":"KEIN HING INTERNATIONAL BHD"},{"stock":"KEN","name":"KEN HOLDINGS BHD"},{"stock":"KENANGA","name":"K & N KENANGA HOLDINGS BHD"},{"stock":"KERJAYA","name":"FUTUTECH BHD"},{"stock":"KERJAYA-WA","name":"FUTUTECH BHD-WA"},{"stock":"KESM","name":"KESM INDUSTRIES BHD"},{"stock":"KEYASIC","name":"KEY ASIC BHD"},{"stock":"KFIMA","name":"KUMPULAN FIMA BHD"},{"stock":"KFM","name":"KUANTAN FLOUR MILLS BHD"},{"stock":"KGB","name":"KELINGTON GROUP BERHAD"},{"stock":"KGB-WA","name":"KELINGTON GROUP BERHAD"},{"stock":"KGROUP","name":"DVM TECHNOLOGY BHD"},{"stock":"KGROUP-WA","name":"DVM TECHNOLOGY BHD-WARR 13/18"},{"stock":"KHEESAN","name":"KHEE SAN BHD"},{"stock":"KHIND","name":"KHIND HOLDINGS BHD"},{"stock":"KIALIM","name":"KIA LIM BHD"},{"stock":"KIANJOO","name":"KIAN JOO CAN FACTORY BHD"},{"stock":"KIMHIN","name":"KIM HIN INDUSTRY BHD"},{"stock":"KIMLUN","name":"KIMLUN CORPORATION BERHAD"},{"stock":"KIMLUN-WA","name":"KIMLUN CORPORATION BERHAD"},{"stock":"KINSTEL","name":"KINSTEEL BHD"},{"stock":"KKB","name":"KKB ENGINEERING BHD"},{"stock":"KLCC","name":"KLCC PROP&REITS-STAPLED SEC"},{"stock":"KLK","name":"KUALA LUMPUR KEPONG BHD"},{"stock":"KLK-CY","name":"KLK-CY: CW KUALA LUMPUR KEPONG BHD (KIBB)"},{"stock":"KLUANG","name":"KLUANG RUBBER CO (M) BHD"},{"stock":"KMLOONG","name":"KIM LOONG RESOURCES BHD"},{"stock":"KNM","name":"KNM GROUP BHD"},{"stock":"KNM-WA","name":"KNM GROUP BHD-WARRANTS 12/17"},{"stock":"KNM-WB","name":"KNM GROUP BHD"},{"stock":"KNUSFOR","name":"KNUSFORD BHD"},{"stock":"KOBAY","name":"KOBAY TECHNOLOGY BHD"},{"stock":"KOMARK","name":"KOMARKCORP BHD"},{"stock":"KOMARK-WB","name":"KOMARKCORP BHD"},{"stock":"KOSSAN","name":"KOSSAN RUBBER INDUSTRIES BHD"},{"stock":"KOSSAN-CM","name":"KOSSAN-CM: CW KOSSAN RUBBER INDUSTRIES BHD (MIBB)"},{"stock":"KOSSAN-CN","name":"KOSSAN-CN: CW KOSSAN RUBBER INDUSTRIES BHD (MIBB)"},{"stock":"KOSSAN-CO","name":"KOSSAN-CO: CW KOSSAN RUBBER INDUSTRIES BHD (KIBB)"},{"stock":"KOSSAN-CQ","name":"KOSSAN-CQ: CW KOSSAN RUBBER INDUSTRIES BHD (KIBB)"},{"stock":"KOSSAN-CR","name":"KOSSAN-CR: CW KOSSAN RUBBER INDUSTRIES BERHAD (MIBB)"},{"stock":"KOSSAN-CS","name":"KOSSAN-CS: CW KOSSAN RUBBER INDUSTRIES BERHAD (MIBB)"},{"stock":"KOSSAN-CT","name":"KOSSAN-CT: CW KOSSAN RUBBER INDUSTRIES BERHAD (MIBB)"},{"stock":"KOTRA","name":"KOTRA INDUSTRIES BHD"},{"stock":"KPJ","name":"KPJ HEALTHCARE BHD"},{"stock":"KPJ-WB","name":"KPJ HEALTHCARE BHD"},{"stock":"KPOWER","name":"KUMPULAN POWERNET BHD"},{"stock":"KPS","name":"KUMPULAN PERANGSANG SELANGOR"},{"stock":"KPSCB","name":"KPS CONSORTIUM BHD"},{"stock":"KRETAM","name":"KRETAM HOLDINGS BHD"},{"stock":"KRONO","name":"KRONOLOGI ASIA BERHAD"},{"stock":"KSENG","name":"KECK SENG (M) BHD"},{"stock":"KSL","name":"KSL HOLDINGS BHD"},{"stock":"KSL-CG","name":"KSL-CG: CW KSL HOLDINGS BERHAD (KIBB)"},{"stock":"KSSC","name":"K. SENG SENG CORPORATION BHD"},{"stock":"KSTAR","name":"K-STAR SPORTS LIMITED"},{"stock":"KTB","name":"KONSORTIUM TRANSNASIONAL BHD"},{"stock":"KTC","name":"KIM TECK CHEONG CONSOLIDATED BERHAD"},{"stock":"KUB","name":"KUB MALAYSIA BHD"},{"stock":"KUCHAI","name":"KUCHAI DEVELOPMENT BHD"},{"stock":"KWANTAS","name":"KWANTAS CORPORATION BHD"},{"stock":"KYM","name":"KYM HOLDINGS BHD"}]