[{"name":"GADANG","ticker":"9261","category":"Bursa Malaysia Construction Stock","company":"GADANG HOLDINGS BHD"},{"name":"GADANG-WB","ticker":"9261WB","category":"Bursa Malaysia Warrants Stock","company":"GADANG-WB"},{"name":"GAMUDA","ticker":"5398","category":"Bursa Malaysia Construction Stock","company":"GAMUDA BERHAD"},{"name":"GAMUDA-WE","ticker":"5398WE","category":"Bursa Malaysia Warrants Stock","company":"GAMUDA-WE"},{"name":"GASMSIA","ticker":"5209","category":"Bursa Malaysia Trading-Services Stock","company":"GAS MALAYSIA BERHAD"},{"name":"GBGAQRS","ticker":"5226","category":"Bursa Malaysia CONSTRUCTION Stock","company":"GABUNGAN AQRS BERHAD"},{"name":"GBGAQRS-WA","ticker":"5226WA","category":"Bursa Malaysia Warrants Stock","company":"GBGAQRS-WA"},{"name":"GBH","ticker":"3611","category":"Bursa Malaysia Industrial Products Stock","company":"GOH BAN HUAT BERHAD"},{"name":"GBH-WA","ticker":"3611WA","category":"Bursa Malaysia Warrants Stock","company":"GBH-WA"},{"name":"GCB","ticker":"5102","category":"Bursa Malaysia Consumer Products Stock","company":"GUAN CHONG BERHAD"},{"name":"GCE","ticker":"5592","category":"Bursa Malaysia Hotels Stock","company":"GRAND CENTRAL ENTERPRISES BHD"},{"name":"GDEX","ticker":"0078","category":"Bursa Malaysia Trading-Services Stock","company":"GD EXPRESS CARRIER BERHAD"},{"name":"GDEX-WB","ticker":"0078WB","category":"Bursa Malaysia Warrants Stock","company":"GDEX-WB"},{"name":"GENETEC","ticker":"0104","category":"Bursa Malaysia Technology Stock","company":"GENETEC TECHNOLOGY BERHAD"},{"name":"GENM","ticker":"4715","category":"Bursa Malaysia Trading-Services Stock","company":"GENTING MALAYSIA BERHAD"},{"name":"GENP","ticker":"2291","category":"Bursa Malaysia Plantation Stock","company":"GENTING PLANTATIONS BERHAD"},{"name":"GENP-WA","ticker":"2291WA","category":"Bursa Malaysia Warrants Stock","company":"GENP-WA"},{"name":"GENTING","ticker":"3182","category":"Bursa Malaysia Trading-Services Stock","company":"GENTING BERHAD"},{"name":"GENTING-WA","ticker":"3182WA","category":"Bursa Malaysia Warrants Stock","company":"GENTING-WA"},{"name":"GESHEN","ticker":"7197","category":"Bursa Malaysia Industrial Products Stock","company":"GE-SHEN CORPORATION BERHAD"},{"name":"GFM","ticker":"0039","category":"Bursa Malaysia Technology Stock","company":"GFM SERVICES BERHAD"},{"name":"GHLSYS","ticker":"0021","category":"Bursa Malaysia Technology Stock","company":"GHL SYSTEMS BERHAD"},{"name":"GKENT","ticker":"3204","category":"Bursa Malaysia Trading-Services Stock","company":"GEORGE KENT (MALAYSIA) BERHAD"},{"name":"GLBHD","ticker":"7382","category":"Bursa Malaysia Plantation Stock","company":"GOLDEN LAND BERHAD"},{"name":"GLOMAC","ticker":"5020","category":"Bursa Malaysia Properties Stock","company":"GLOMAC BERHAD"},{"name":"GLOTEC","ticker":"5220","category":"Bursa Malaysia Industrial Products Stock","company":"GLOBALTEC FORMATION BERHAD"},{"name":"GMUTUAL","ticker":"9962","category":"Bursa Malaysia Properties Stock","company":"GROMUTUAL BERHAD"},{"name":"GNB","ticker":"0045","category":"Bursa Malaysia Technology Stock","company":"G NEPTUNE BERHAD"},{"name":"GOB","ticker":"1147","category":"Bursa Malaysia Properties Stock","company":"GLOBAL ORIENTAL BERHAD"},{"name":"GOB-WA","ticker":"1147WA","category":"Bursa Malaysia Warrants Stock","company":"GOB-WA"},{"name":"GOCEAN","ticker":"0074","category":"Bursa Malaysia Technology Stock","company":"GREEN OCEAN CORPORATION BERHAD"},{"name":"GOCEAN-WA","ticker":"0074WA","category":"Bursa Malaysia Warrants Stock","company":"GOCEAN-WA"},{"name":"GOLDIS","ticker":"5606","category":"Bursa Malaysia Consumer Products Stock","company":"GOLDIS BERHAD"},{"name":"GOODWAY","ticker":"7192","category":"Bursa Malaysia Industrial Products Stock","company":"GOODWAY INTEGRATED INDUSTRIES BERHAD"},{"name":"GOPENG","ticker":"2135","category":"Bursa Malaysia Plantation Stock","company":"GOPENG BERHAD"},{"name":"GPA","ticker":"7096","category":"Bursa Malaysia Industrial Products Stock","company":"GPA HOLDINGS BERHAD"},{"name":"GPA-WA","ticker":"7096WA","category":"Bursa Malaysia Warrants Stock","company":"GPA-WA"},{"name":"GPACKET","ticker":"0082","category":"Bursa Malaysia Technology Stock","company":"GREEN PACKET BERHAD"},{"name":"GPHAROS","ticker":"5649","category":"Bursa Malaysia Industrial Products Stock","company":"GOLDEN PHAROS BERHAD"},{"name":"GRANFLO","ticker":"0056","category":"Bursa Malaysia Technology Stock","company":"GRAND-FLO BERHAD"},{"name":"GREENYB","ticker":"0136","category":"Bursa Malaysia Industrial Products Stock","company":"GREENYIELD BERHAD"},{"name":"GSB","ticker":"7077","category":"Bursa Malaysia Properties Stock","company":"GSB GROUP BERHAD"},{"name":"GTRONIC","ticker":"7022","category":"Bursa Malaysia Technology Stock","company":"GLOBETRONICS TECHNOLOGY BERHAD"},{"name":"GUH","ticker":"3247","category":"Bursa Malaysia Industrial Products Stock","company":"GUH HOLDINGS BERHAD"},{"name":"GUNUNG","ticker":"7676","category":"Bursa Malaysia Trading-Services Stock","company":"GUNUNG CAPITAL BERHAD"},{"name":"GUNUNG-WB","ticker":"7676WB","category":"Bursa Malaysia Warrants Stock","company":"GUNUNG-WB"},{"name":"GUOCO","ticker":"1503","category":"Bursa Malaysia Properties Stock","company":"GUOCOLAND (MALAYSIA) BERHAD"}]