[{"name":"Y&G","ticker":"7003","category":"Bursa Malaysia Properties Stock","company":"Y&G CORPORATION BHD"},{"name":"Y&G-WA","ticker":"7003WA","category":"Bursa Malaysia Warrants Stock","company":"Y&G-WA"},{"name":"YEELEE","ticker":"5584","category":"Bursa Malaysia Consumer Products Stock","company":"YEE LEE CORPORATION BHD"},{"name":"YEN","ticker":"7184","category":"Bursa Malaysia Consumer Products Stock","company":"YEN GLOBAL BERHAD"},{"name":"YFG","ticker":"7122","category":"Bursa Malaysia Trading-Services Stock","company":"YFG BERHAD"},{"name":"YGL","ticker":"0086","category":"Bursa Malaysia Technology Stock","company":"YGL CONVERGENCE BERHAD"},{"name":"YILAI","ticker":"5048","category":"Bursa Malaysia Industrial Products Stock","company":"YI-LAI BERHAD"},{"name":"YINSON","ticker":"7293","category":"Bursa Malaysia Trading-Services Stock","company":"YINSON HOLDINGS BERHAD"},{"name":"YKGI","ticker":"7020","category":"Bursa Malaysia Industrial Products Stock","company":"YKGI HOLDINGS BERHAD"},{"name":"YKGI-WB","ticker":"7020WB","category":"Bursa Malaysia Warrants Stock","company":"YKGI-WB"},{"name":"YLI","ticker":"7014","category":"Bursa Malaysia Industrial Products Stock","company":"YLI HOLDINGS BERHAD"},{"name":"YNHPROP","ticker":"3158","category":"Bursa Malaysia Properties Stock","company":"YNH PROPERTY BERHAD"},{"name":"YOCB","ticker":"5159","category":"Bursa Malaysia Consumer Products Stock","company":"YOONG ONN CORPORATION BERHAD"},{"name":"YONGTAI","ticker":"7066","category":"Bursa Malaysia Trading-Services Stock","company":"YONG TAI BERHAD"},{"name":"YONGTAI-WA","ticker":"7066WA","category":"Bursa Malaysia Warrants Stock","company":"YONGTAI-WA"},{"name":"YSPSAH","ticker":"7178","category":"Bursa Malaysia Consumer Products Stock","company":"Y.S.P.SOUTHEAST ASIA HOLDING BERHAD"},{"name":"YTL","ticker":"4677","category":"Bursa Malaysia Trading-Services Stock","company":"YTL CORPORATION BERHAD"},{"name":"YTLLAND","ticker":"2577","category":"Bursa Malaysia Properties Stock","company":"YTL LAND & DEVELOPMENT BERHAD"},{"name":"YTLPOWR","ticker":"6742","category":"Bursa Malaysia IPC Stock","company":"YTL POWER INTERNATIONAL BHD"},{"name":"YTLPOWR-WB","ticker":"6742WB","category":"Bursa Malaysia Warrants Stock","company":"YTLPOWR-WB"},{"name":"YTLREIT","ticker":"5109","category":"Bursa Malaysia REITs Stock","company":"YTL HOSPITALITY REIT"}]